tk002_zadaca2_mehmedovic_amar/zad3/top.vhd
library IEEE;
use IEEE.STD_LOGIC_1164.ALL;
use ieee.numeric_std.all;

entity top is
	port (led: out std_logic := '0';
		  dtx: out std_logic;
		  par: inout unsigned(1 downto 0):="00";
		  fclk: in  std_logic);
end top;

architecture arctop of top is
signal data: unsigned (7 downto 0) := x"28";
signal tled: std_logic := '0';

begin
	process (fclk)
		variable state:integer:=0;
		variable pause:integer:=9;
		variable cnt:integer:=0;
		variable idx:integer:=0;
		variable cnter_parity:integer:=0;
		variable stop_idle:boolean:=false;
		variable baudrate:integer:=6; --> 921600 Bauds -> 54 clocks of 50MHz 108->100MHz
		--variable baudrate:integer:=434;				--> 115200 Bauds -> 434 clocks of 50MHz 
		
		begin
			if fclk'event and fclk='1' then
				if(stop_idle=false)then
				dtx<='1';
					end if;
							cnt := cnt + 1;
				if(state = 0) then						-- generate start bit
					if(cnt = pause) then				-- ? can we remove this and unify?
						cnt := 0;
						state := state + 1;
						pause := baudrate; 
						-- start bit
						dtx <= '0';
						stop_idle:=true;
						tled <= tled  xor '1';
						led <= tled;
					end if;
				elsif(state <= 8) then					-- data
					if(cnt = pause) then
						cnt := 0;
						state := state + 1;
						pause := baudrate;
						
						-- data
						dtx <= data(idx);
						if(data(idx)='1')then
							cnter_parity:=cnter_parity+1;
						end if;
						idx := idx + 1;
					end if;
				elsif(state = 9) then					--parity
					if(cnt=pause)then
						cnt:=0;
						state:=state+1;	
						pause:=baudrate;
						if(cnter_parity mod 2)=0 then
						par<="01";
						else
						par<="10";
					end if;
				dtx<='1';
				end if;
				elsif(state=10)then
					if(cnt = pause) then
						cnt := 0;
						state := state + 1;
						pause := baudrate;
						
						-- stop bit
						dtx <= '1';
					end if;	
				else
					if(cnt = pause) then
						cnt := 0;
						state := 0;
						pause := 9;
						dtx <= '1';
						idx:=0;
						data <= data - x"01";
						par<="00";
						cnter_parity:=0;
						tled<='0';
						stop_idle:=false;
						if(to_integer(data) < 5) then
							data <= x"28";
						end if;
					end if;	
				end if;
			end if;
	end process;	

end arctop;

tk002_zadaca2_mehmedovic_amar/zad3/top_tb.vhd
library IEEE;
use IEEE.STD_LOGIC_1164.ALL;
use ieee.numeric_std.all;

entity top_tb is
end top_tb;

architecture arctop_tb of top_tb is
	component top
	port (led: out std_logic := '0';
		  dtx: out std_logic;
		  par: inout unsigned(1 downto 0):="00";
		  fclk: in  std_logic);
	end component;


signal fclk:std_logic:='0';
signal led:std_logic:='0';
signal dtx:std_logic;
signal endsim:std_logic:='0';
signal par:unsigned(1 downto 0):="00";

begin 
	uart: top port map(fclk=>fclk,led=>led,dtx=>dtx,par=>par);

	clk: process
		variable fclk_end: integer:=200;
		variable fclk_cnt: integer:=0;
	begin
		fclk<='1';
		wait for 5 ns;
		fclk <='0';
		wait for 5 ns;
		fclk_cnt:=fclk_cnt+1;
		if(fclk_cnt=fclk_end)then
			report "fpga clock exhausted";
			endsim<='1';
			wait;
		end if;

		if(endsim='1')then
			report "fpga clock shutdown";
			wait;
		end if;
	end process;
end arctop_tb;

tk002_zadaca2_mehmedovic_amar/zad3/top.vcd
$date
  Sun Jul  3 16:28:55 2022
$end
$version
  GHDL v0
$end
$timescale
  1 fs
$end
$scope module standard $end
$upscope $end
$scope module std_logic_1164 $end
$upscope $end
$scope module numeric_std $end
$upscope $end
$scope module top_tb $end
$var reg 1 ! fclk $end
$var reg 1 " led $end
$var reg 1 # dtx $end
$var reg 1 $ endsim $end
$var reg 2 % par[1:0] $end
$scope module uart $end
$var reg 1 & led $end
$var reg 1 ' dtx $end
$var reg 2 ( par[1:0] $end
$var reg 1 ) fclk $end
$var reg 8 * data[7:0] $end
$var reg 1 + tled $end
$upscope $end
$upscope $end
$enddefinitions $end
#0
1!
0"
1#
0$
b00 %
0&
1'
b00 (
1)
b00101000 *
0+
#5000000
0!
0)
#10000000
1!
1)
#15000000
0!
0)
#20000000
1!
1)
#25000000
0!
0)
#30000000
1!
1)
#35000000
0!
0)
#40000000
1!
1)
#45000000
0!
0)
#50000000
1!
1)
#55000000
0!
0)
#60000000
1!
1)
#65000000
0!
0)
#70000000
1!
1)
#75000000
0!
0)
#80000000
1!
0#
0'
1)
1+
#85000000
0!
0)
#90000000
1!
1)
#95000000
0!
0)
#100000000
1!
1)
#105000000
0!
0)
#110000000
1!
1)
#115000000
0!
0)
#120000000
1!
1)
#125000000
0!
0)
#130000000
1!
1)
#135000000
0!
0)
#140000000
1!
1)
#145000000
0!
0)
#150000000
1!
1)
#155000000
0!
0)
#160000000
1!
1)
#165000000
0!
0)
#170000000
1!
1)
#175000000
0!
0)
#180000000
1!
1)
#185000000
0!
0)
#190000000
1!
1)
#195000000
0!
0)
#200000000
1!
1)
#205000000
0!
0)
#210000000
1!
1)
#215000000
0!
0)
#220000000
1!
1)
#225000000
0!
0)
#230000000
1!
1)
#235000000
0!
0)
#240000000
1!
1)
#245000000
0!
0)
#250000000
1!
1)
#255000000
0!
0)
#260000000
1!
1)
#265000000
0!
0)
#270000000
1!
1)
#275000000
0!
0)
#280000000
1!
1)
#285000000
0!
0)
#290000000
1!
1)
#295000000
0!
0)
#300000000
1!
1)
#305000000
0!
0)
#310000000
1!
1)
#315000000
0!
0)
#320000000
1!
1#
1'
1)
#325000000
0!
0)
#330000000
1!
1)
#335000000
0!
0)
#340000000
1!
1)
#345000000
0!
0)
#350000000
1!
1)
#355000000
0!
0)
#360000000
1!
1)
#365000000
0!
0)
#370000000
1!
1)
#375000000
0!
0)
#380000000
1!
0#
0'
1)
#385000000
0!
0)
#390000000
1!
1)
#395000000
0!
0)
#400000000
1!
1)
#405000000
0!
0)
#410000000
1!
1)
#415000000
0!
0)
#420000000
1!
1)
#425000000
0!
0)
#430000000
1!
1)
#435000000
0!
0)
#440000000
1!
1#
1'
1)
#445000000
0!
0)
#450000000
1!
1)
#455000000
0!
0)
#460000000
1!
1)
#465000000
0!
0)
#470000000
1!
1)
#475000000
0!
0)
#480000000
1!
1)
#485000000
0!
0)
#490000000
1!
1)
#495000000
0!
0)
#500000000
1!
0#
0'
1)
#505000000
0!
0)
#510000000
1!
1)
#515000000
0!
0)
#520000000
1!
1)
#525000000
0!
0)
#530000000
1!
1)
#535000000
0!
0)
#540000000
1!
1)
#545000000
0!
0)
#550000000
1!
1)
#555000000
0!
0)
#560000000
1!
1)
#565000000
0!
0)
#570000000
1!
1)
#575000000
0!
0)
#580000000
1!
1)
#585000000
0!
0)
#590000000
1!
1)
#595000000
0!
0)
#600000000
1!
1)
#605000000
0!
0)
#610000000
1!
1)
#615000000
0!
0)
#620000000
1!
1#
b01 %
1'
b01 (
1)
#625000000
0!
0)
#630000000
1!
1)
#635000000
0!
0)
#640000000
1!
1)
#645000000
0!
0)
#650000000
1!
1)
#655000000
0!
0)
#660000000
1!
1)
#665000000
0!
0)
#670000000
1!
1)
#675000000
0!
0)
#680000000
1!
1)
#685000000
0!
0)
#690000000
1!
1)
#695000000
0!
0)
#700000000
1!
1)
#705000000
0!
0)
#710000000
1!
1)
#715000000
0!
0)
#720000000
1!
1)
#725000000
0!
0)
#730000000
1!
1)
#735000000
0!
0)
#740000000
1!
b00 %
b00 (
1)
b00100111 *
0+
#745000000
0!
0)
#750000000
1!
1)
#755000000
0!
0)
#760000000
1!
1)
#765000000
0!
0)
#770000000
1!
1)
#775000000
0!
0)
#780000000
1!
1)
#785000000
0!
0)
#790000000
1!
1)
#795000000
0!
0)
#800000000
1!
1)
#805000000
0!
0)
#810000000
1!
1)
#815000000
0!
0)
#820000000
1!
1)
#825000000
0!
0)
#830000000
1!
0#
0'
1)
1+
#835000000
0!
0)
#840000000
1!
1)
#845000000
0!
0)
#850000000
1!
1)
#855000000
0!
0)
#860000000
1!
1)
#865000000
0!
0)
#870000000
1!
1)
#875000000
0!
0)
#880000000
1!
1)
#885000000
0!
0)
#890000000
1!
1#
1'
1)
#895000000
0!
0)
#900000000
1!
1)
#905000000
0!
0)
#910000000
1!
1)
#915000000
0!
0)
#920000000
1!
1)
#925000000
0!
0)
#930000000
1!
1)
#935000000
0!
0)
#940000000
1!
1)
#945000000
0!
0)
#950000000
1!
1)
#955000000
0!
0)
#960000000
1!
1)
#965000000
0!
0)
#970000000
1!
1)
#975000000
0!
0)
#980000000
1!
1)
#985000000
0!
0)
#990000000
1!
1)
#995000000
0!
0)
#1000000000
1!
1)
#1005000000
0!
0)
#1010000000
1!
1)
#1015000000
0!
0)
#1020000000
1!
1)
#1025000000
0!
0)
#1030000000
1!
1)
#1035000000
0!
0)
#1040000000
1!
1)
#1045000000
0!
0)
#1050000000
1!
1)
#1055000000
0!
0)
#1060000000
1!
1)
#1065000000
0!
0)
#1070000000
1!
0#
0'
1)
#1075000000
0!
0)
#1080000000
1!
1)
#1085000000
0!
0)
#1090000000
1!
1)
#1095000000
0!
0)
#1100000000
1!
1)
#1105000000
0!
0)
#1110000000
1!
1)
#1115000000
0!
0)
#1120000000
1!
1)
#1125000000
0!
0)
#1130000000
1!
1)
#1135000000
0!
0)
#1140000000
1!
1)
#1145000000
0!
0)
#1150000000
1!
1)
#1155000000
0!
0)
#1160000000
1!
1)
#1165000000
0!
0)
#1170000000
1!
1)
#1175000000
0!
0)
#1180000000
1!
1)
#1185000000
0!
0)
#1190000000
1!
1#
1'
1)
#1195000000
0!
0)
#1200000000
1!
1)
#1205000000
0!
0)
#1210000000
1!
1)
#1215000000
0!
0)
#1220000000
1!
1)
#1225000000
0!
0)
#1230000000
1!
1)
#1235000000
0!
0)
#1240000000
1!
1)
#1245000000
0!
0)
#1250000000
1!
0#
0'
1)
#1255000000
0!
0)
#1260000000
1!
1)
#1265000000
0!
0)
#1270000000
1!
1)
#1275000000
0!
0)
#1280000000
1!
1)
#1285000000
0!
0)
#1290000000
1!
1)
#1295000000
0!
0)
#1300000000
1!
1)
#1305000000
0!
0)
#1310000000
1!
1)
#1315000000
0!
0)
#1320000000
1!
1)
#1325000000
0!
0)
#1330000000
1!
1)
#1335000000
0!
0)
#1340000000
1!
1)
#1345000000
0!
0)
#1350000000
1!
1)
#1355000000
0!
0)
#1360000000
1!
1)
#1365000000
0!
0)
#1370000000
1!
1#
b01 %
1'
b01 (
1)
#1375000000
0!
0)
#1380000000
1!
1)
#1385000000
0!
0)
#1390000000
1!
1)
#1395000000
0!
0)
#1400000000
1!
1)
#1405000000
0!
0)
#1410000000
1!
1)
#1415000000
0!
0)
#1420000000
1!
1)
#1425000000
0!
0)
#1430000000
1!
1)
#1435000000
0!
0)
#1440000000
1!
1)
#1445000000
0!
0)
#1450000000
1!
1)
#1455000000
0!
0)
#1460000000
1!
1)
#1465000000
0!
0)
#1470000000
1!
1)
#1475000000
0!
0)
#1480000000
1!
1)
#1485000000
0!
0)
#1490000000
1!
b00 %
b00 (
1)
b00100110 *
0+
#1495000000
0!
0)
#1500000000
1!
1)
#1505000000
0!
0)
#1510000000
1!
1)
#1515000000
0!
0)
#1520000000
1!
1)
#1525000000
0!
0)
#1530000000
1!
1)
#1535000000
0!
0)
#1540000000
1!
1)
#1545000000
0!
0)
#1550000000
1!
1)
#1555000000
0!
0)
#1560000000
1!
1)
#1565000000
0!
0)
#1570000000
1!
1)
#1575000000
0!
0)
#1580000000
1!
0#
0'
1)
1+
#1585000000
0!
0)
#1590000000
1!
1)
#1595000000
0!
0)
#1600000000
1!
1)
#1605000000
0!
0)
#1610000000
1!
1)
#1615000000
0!
0)
#1620000000
1!
1)
#1625000000
0!
0)
#1630000000
1!
1)
#1635000000
0!
0)
#1640000000
1!
1)
#1645000000
0!
0)
#1650000000
1!
1)
#1655000000
0!
0)
#1660000000
1!
1)
#1665000000
0!
0)
#1670000000
1!
1)
#1675000000
0!
0)
#1680000000
1!
1)
#1685000000
0!
0)
#1690000000
1!
1)
#1695000000
0!
0)
#1700000000
1!
1#
1'
1)
#1705000000
0!
0)
#1710000000
1!
1)
#1715000000
0!
0)
#1720000000
1!
1)
#1725000000
0!
0)
#1730000000
1!
1)
#1735000000
0!
0)
#1740000000
1!
1)
#1745000000
0!
0)
#1750000000
1!
1)
#1755000000
0!
0)
#1760000000
1!
1)
#1765000000
0!
0)
#1770000000
1!
1)
#1775000000
0!
0)
#1780000000
1!
1)
#1785000000
0!
0)
#1790000000
1!
1)
#1795000000
0!
0)
#1800000000
1!
1)
#1805000000
0!
0)
#1810000000
1!
1)
#1815000000
0!
0)
#1820000000
1!
0#
0'
1)
#1825000000
0!
0)
#1830000000
1!
1)
#1835000000
0!
0)
#1840000000
1!
1)
#1845000000
0!
0)
#1850000000
1!
1)
#1855000000
0!
0)
#1860000000
1!
1)
#1865000000
0!
0)
#1870000000
1!
1)
#1875000000
0!
0)
#1880000000
1!
1)
#1885000000
0!
0)
#1890000000
1!
1)
#1895000000
0!
0)
#1900000000
1!
1)
#1905000000
0!
0)
#1910000000
1!
1)
#1915000000
0!
0)
#1920000000
1!
1)
#1925000000
0!
0)
#1930000000
1!
1)
#1935000000
0!
0)
#1940000000
1!
1#
1'
1)
#1945000000
0!
0)
#1950000000
1!
1)
#1955000000
0!
0)
#1960000000
1!
1)
#1965000000
0!
0)
#1970000000
1!
1)
#1975000000
0!
0)
#1980000000
1!
1)
#1985000000
0!
0)
#1990000000
1!
1)
#1995000000
0!
0)
#2000000000
1$
